scrapy_redis_bloomfilter/__init__.py
scrapy_redis_bloomfilter/bloomfilter.py
scrapy_redis_bloomfilter/bloomfilter_bak.py
scrapy_redis_bloomfilter/connection.py
scrapy_redis_bloomfilter/defaults.py
scrapy_redis_bloomfilter/dupefilter.py
scrapy_redis_bloomfilter/picklecompat.py
scrapy_redis_bloomfilter/pipelines.py
scrapy_redis_bloomfilter/queue.py
scrapy_redis_bloomfilter/scheduler.py
scrapy_redis_bloomfilter/spiders.py
scrapy_redis_bloomfilter/utils.py
scrapy_redis_ironman-0.1.0.dist-info/METADATA
scrapy_redis_ironman-0.1.0.dist-info/WHEEL
scrapy_redis_ironman-0.1.0.dist-info/top_level.txt
scrapy_redis_ironman-0.1.0.dist-info/RECORD
